{
  "metadata": {
    "generated_at": "2026-02-01T23:39:29.581688",
    "total_records": 911797,
    "date_range": {
      "start": "1990-01-01",
      "end": "2026-01-01"
    }
  },
  "stats": {
    "whole": {
      "count": 911797,
      "median_price": 332800,
      "median_psf": 307,
      "volume": 911797
    },
    "pre_covid": {
      "count": 741823,
      "median_price": 283500,
      "median_psf": 265,
      "volume": 741823
    },
    "recent": {
      "count": 169974,
      "median_price": 1028888,
      "median_psf": 1177,
      "volume": 169974
    }
  },
  "distributions": {
    "property_type": {
      "HDB": 785395,
      "Condominium": 109576,
      "EC": 16826
    },
    "planning_area": {
      "QUEENSTOWN": 113261,
      "WOODLANDS": 75935,
      "YISHUN": 69018,
      "TAMPINES": 68347,
      "ANG MO KIO": 59288,
      "HOUGANG": 51133,
      "JURONG WEST": 47582,
      "CHOA CHU KANG": 45109,
      "BEDOK": 38589,
      "PASIR RIS": 38485
    }
  }
}